ovos_skill_ddg/__init__.py
ovos_skill_ddg/version.py
ovos_skill_ddg/gui/all/ddg.png
ovos_skill_ddg/gui/all/logo.png
ovos_skill_ddg/gui/qt5/DuckDelegate.qml
ovos_skill_ddg/locale/ca-es/MiscBlacklist.voc
ovos_skill_ddg/locale/ca-es/More.voc
ovos_skill_ddg/locale/ca-es/Weather.voc
ovos_skill_ddg/locale/ca-es/age_at_death.intent
ovos_skill_ddg/locale/ca-es/alma_mater.intent
ovos_skill_ddg/locale/ca-es/birthdate.intent
ovos_skill_ddg/locale/ca-es/born.intent
ovos_skill_ddg/locale/ca-es/children.intent
ovos_skill_ddg/locale/ca-es/died.intent
ovos_skill_ddg/locale/ca-es/education.intent
ovos_skill_ddg/locale/ca-es/fields.intent
ovos_skill_ddg/locale/ca-es/known_for.intent
ovos_skill_ddg/locale/ca-es/no_answer.dialog
ovos_skill_ddg/locale/ca-es/official_website.intent
ovos_skill_ddg/locale/ca-es/resting_place.intent
ovos_skill_ddg/locale/ca-es/search_duck.intent
ovos_skill_ddg/locale/ca-es/skill.json
ovos_skill_ddg/locale/ca-es/thats all.dialog
ovos_skill_ddg/locale/ca-es/thesis.intent
ovos_skill_ddg/locale/ca-es/who.intent
ovos_skill_ddg/locale/da-dk/More.voc
ovos_skill_ddg/locale/da-dk/age_at_death.intent
ovos_skill_ddg/locale/da-dk/alma_mater.intent
ovos_skill_ddg/locale/da-dk/birthdate.intent
ovos_skill_ddg/locale/da-dk/born.intent
ovos_skill_ddg/locale/da-dk/children.intent
ovos_skill_ddg/locale/da-dk/died.intent
ovos_skill_ddg/locale/da-dk/education.intent
ovos_skill_ddg/locale/da-dk/fields.intent
ovos_skill_ddg/locale/da-dk/known_for.intent
ovos_skill_ddg/locale/da-dk/no_answer.dialog
ovos_skill_ddg/locale/da-dk/official_website.intent
ovos_skill_ddg/locale/da-dk/resting_place.intent
ovos_skill_ddg/locale/da-dk/search_duck.intent
ovos_skill_ddg/locale/da-dk/skill.json
ovos_skill_ddg/locale/da-dk/thats all.dialog
ovos_skill_ddg/locale/da-dk/thesis.intent
ovos_skill_ddg/locale/da-dk/who.intent
ovos_skill_ddg/locale/de-de/MiscBlacklist.voc
ovos_skill_ddg/locale/de-de/More.voc
ovos_skill_ddg/locale/de-de/Weather.voc
ovos_skill_ddg/locale/de-de/age_at_death.intent
ovos_skill_ddg-0.3.6.dist-info/licenses/LICENSE
ovos_skill_ddg-0.3.6.dist-info/METADATA
ovos_skill_ddg-0.3.6.dist-info/WHEEL
ovos_skill_ddg-0.3.6.dist-info/entry_points.txt
ovos_skill_ddg-0.3.6.dist-info/top_level.txt
ovos_skill_ddg-0.3.6.dist-info/RECORD
