Metadata-Version: 2.4
Name: ovos_skill_ddg
Version: 0.3.6
Summary: ovos duck duck go skill plugin
Home-page: https://github.com/OpenVoiceOS/ovos-skill-ddg
Author: JarbasAi
Author-email: jarbasai@mailfence.com
License: Apache-2.0
Keywords: ovos skill plugin
License-File: LICENSE
Requires-Dist: requests
Requires-Dist: langcodes
Requires-Dist: ovos_workshop<8.0.0,>=3.4.0
Requires-Dist: ovos-translate-server-plugin
Requires-Dist: ovos-plugin-manager<3.0.0,>=0.0.26
Requires-Dist: ovos-date-parser
Requires-Dist: crf_query_xtract<1.0.0,>=0.1.2
Requires-Dist: brill_postagger<1.0.0,>=0.1.2
Dynamic: author
Dynamic: author-email
Dynamic: description
Dynamic: description-content-type
Dynamic: home-page
Dynamic: keywords
Dynamic: license
Dynamic: license-file
Dynamic: requires-dist
Dynamic: summary
